{
  "modelVersion" : "2.2",
  "id" : "newForm55",
  "name" : "newForm55",
  "lastUpdate" : 1702933401053,
  "rows" : [
    [
      {
        "type" : "formContainer",
        "dimension" : {
          "xs" : 12
        },
        "propertyValues" : { },
        "reference" : "30049130-b9e6-486f-bb23-85d7ffa397d1",
        "hasValidationError" : false,
        "id" : "pbFormContainer",
        "container" : {
          "type" : "container",
          "dimension" : {
            "xs" : 12
          },
          "propertyValues" : { },
          "reference" : "b32e624f-158e-4fa9-a6f2-f3548432d75c",
          "hasValidationError" : false,
          "id" : "pbContainer",
          "rows" : [
            [
              {
                "type" : "component",
                "dimension" : {
                  "md" : 12,
                  "sm" : 12,
                  "xs" : 12,
                  "lg" : 12
                },
                "propertyValues" : {
                  "hidden" : {
                    "type" : "constant",
                    "value" : false
                  },
                  "level" : {
                    "type" : "constant",
                    "value" : "Level 4"
                  },
                  "cssClasses" : {
                    "type" : "constant",
                    "value" : ""
                  },
                  "text" : {
                    "type" : "interpolation",
                    "value" : "Zahtev Za Kodifikaciju"
                  },
                  "alignment" : {
                    "type" : "constant",
                    "value" : "left"
                  },
                  "dimension" : {
                    "type" : "constant",
                    "value" : 12
                  }
                },
                "reference" : "62123d92-5dd1-4447-88ba-0be86a159f71",
                "hasValidationError" : false,
                "id" : "pbTitle",
                "description" : ""
              }
            ],
            [
              {
                "type" : "container",
                "dimension" : {
                  "md" : 12,
                  "sm" : 12,
                  "xs" : 12,
                  "lg" : 12
                },
                "propertyValues" : {
                  "repeatedCollection" : {
                    "type" : "variable"
                  },
                  "hidden" : {
                    "type" : "constant",
                    "value" : false
                  },
                  "cssClasses" : {
                    "type" : "constant",
                    "value" : ""
                  },
                  "dimension" : {
                    "type" : "constant",
                    "value" : 12
                  }
                },
                "reference" : "903d822a-449f-4c35-a25a-783915dd433e",
                "hasValidationError" : false,
                "id" : "pbContainer",
                "rows" : [
                  [
                    {
                      "type" : "component",
                      "dimension" : {
                        "md" : 12,
                        "sm" : 12,
                        "xs" : 12,
                        "lg" : 12
                      },
                      "propertyValues" : {
                        "hidden" : {
                          "type" : "constant",
                          "value" : false
                        },
                        "level" : {
                          "type" : "constant",
                          "value" : "Level 4"
                        },
                        "cssClasses" : {
                          "type" : "constant",
                          "value" : ""
                        },
                        "text" : {
                          "type" : "interpolation",
                          "value" : "Stavke"
                        },
                        "alignment" : {
                          "type" : "constant",
                          "value" : "left"
                        },
                        "dimension" : {
                          "type" : "constant",
                          "value" : 12
                        }
                      },
                      "reference" : "ccb22036-b786-4750-b839-ac13eca3c202",
                      "hasValidationError" : false,
                      "id" : "pbTitle",
                      "description" : ""
                    }
                  ],
                  [
                    {
                      "type" : "container",
                      "dimension" : {
                        "md" : 12,
                        "sm" : 12,
                        "xs" : 12,
                        "lg" : 12
                      },
                      "propertyValues" : {
                        "repeatedCollection" : {
                          "type" : "variable",
                          "value" : "formInput.zahtevZaKodifikacijuInput.stavke"
                        },
                        "hidden" : {
                          "type" : "constant",
                          "value" : false
                        },
                        "cssClasses" : {
                          "type" : "constant",
                          "value" : ""
                        },
                        "dimension" : {
                          "type" : "constant",
                          "value" : 12
                        }
                      },
                      "reference" : "e56abce2-f147-4246-a17c-7f5a77ce93c0",
                      "hasValidationError" : false,
                      "id" : "pbContainer",
                      "rows" : [
                        [
                          {
                            "type" : "container",
                            "dimension" : {
                              "md" : 12,
                              "sm" : 12,
                              "xs" : 12,
                              "lg" : 12
                            },
                            "propertyValues" : {
                              "repeatedCollection" : {
                                "type" : "variable"
                              },
                              "hidden" : {
                                "type" : "constant",
                                "value" : false
                              },
                              "cssClasses" : {
                                "type" : "constant",
                                "value" : ""
                              },
                              "dimension" : {
                                "type" : "constant",
                                "value" : 12
                              }
                            },
                            "reference" : "8c1ec2a5-23b3-482b-bd96-4f3bd1e9f739",
                            "hasValidationError" : false,
                            "id" : "pbContainer",
                            "rows" : [
                              [
                                {
                                  "type" : "component",
                                  "dimension" : {
                                    "md" : 12,
                                    "sm" : 12,
                                    "xs" : 12,
                                    "lg" : 12
                                  },
                                  "propertyValues" : {
                                    "labelHidden" : {
                                      "type" : "constant",
                                      "value" : false
                                    },
                                    "hidden" : {
                                      "type" : "constant",
                                      "value" : false
                                    },
                                    "labelPosition" : {
                                      "type" : "constant",
                                      "value" : "top"
                                    },
                                    "cssClasses" : {
                                      "type" : "constant",
                                      "value" : ""
                                    },
                                    "labelWidth" : {
                                      "type" : "constant",
                                      "value" : 4
                                    },
                                    "label" : {
                                      "type" : "interpolation",
                                      "value" : "Word_zakona"
                                    },
                                    "placeholder" : {
                                      "type" : "constant",
                                      "value" : "Browse to upload a new file..."
                                    },
                                    "dimension" : {
                                      "type" : "constant",
                                      "value" : 12
                                    },
                                    "value" : {
                                      "type" : "variable",
                                      "value" : "$item.word_zakona"
                                    },
                                    "required" : {
                                      "type" : "constant",
                                      "value" : true
                                    },
                                    "url" : {
                                      "type" : "constant",
                                      "value" : "../API/formFileUpload"
                                    }
                                  },
                                  "reference" : "e74ec853-c26d-49bc-8f92-1de70f1e1445",
                                  "hasValidationError" : false,
                                  "id" : "pbUpload",
                                  "description" : ""
                                }
                              ]
                            ]
                          }
                        ],
                        [
                          {
                            "type" : "container",
                            "dimension" : {
                              "md" : 12,
                              "sm" : 12,
                              "xs" : 12,
                              "lg" : 12
                            },
                            "propertyValues" : {
                              "repeatedCollection" : {
                                "type" : "variable"
                              },
                              "hidden" : {
                                "type" : "constant",
                                "value" : false
                              },
                              "cssClasses" : {
                                "type" : "constant",
                                "value" : ""
                              },
                              "dimension" : {
                                "type" : "constant",
                                "value" : 12
                              }
                            },
                            "reference" : "1b63c406-49ef-4be0-85e1-0d5491346e35",
                            "hasValidationError" : false,
                            "id" : "pbContainer",
                            "rows" : [
                              [
                                {
                                  "type" : "component",
                                  "dimension" : {
                                    "md" : 12,
                                    "sm" : 12,
                                    "xs" : 12,
                                    "lg" : 12
                                  },
                                  "propertyValues" : {
                                    "labelHidden" : {
                                      "type" : "constant",
                                      "value" : false
                                    },
                                    "hidden" : {
                                      "type" : "constant",
                                      "value" : false
                                    },
                                    "labelPosition" : {
                                      "type" : "constant",
                                      "value" : "top"
                                    },
                                    "cssClasses" : {
                                      "type" : "constant",
                                      "value" : ""
                                    },
                                    "labelWidth" : {
                                      "type" : "constant",
                                      "value" : 4
                                    },
                                    "label" : {
                                      "type" : "interpolation",
                                      "value" : "Skeniran_potpisan_zakon"
                                    },
                                    "placeholder" : {
                                      "type" : "constant",
                                      "value" : "Browse to upload a new file..."
                                    },
                                    "dimension" : {
                                      "type" : "constant",
                                      "value" : 12
                                    },
                                    "value" : {
                                      "type" : "variable",
                                      "value" : "$item.skeniran_potpisan_zakon"
                                    },
                                    "required" : {
                                      "type" : "constant",
                                      "value" : true
                                    },
                                    "url" : {
                                      "type" : "constant",
                                      "value" : "../API/formFileUpload"
                                    }
                                  },
                                  "reference" : "cd304f74-0360-4704-b78b-ca45d5fde0f7",
                                  "hasValidationError" : false,
                                  "id" : "pbUpload",
                                  "description" : ""
                                }
                              ]
                            ]
                          }
                        ],
                        [
                          {
                            "type" : "container",
                            "dimension" : {
                              "md" : 12,
                              "sm" : 12,
                              "xs" : 12,
                              "lg" : 12
                            },
                            "propertyValues" : {
                              "repeatedCollection" : {
                                "type" : "variable"
                              },
                              "hidden" : {
                                "type" : "constant",
                                "value" : false
                              },
                              "cssClasses" : {
                                "type" : "constant",
                                "value" : ""
                              },
                              "dimension" : {
                                "type" : "constant",
                                "value" : 12
                              }
                            },
                            "reference" : "56560577-1e61-43e8-bca6-2ff54ea9f78c",
                            "hasValidationError" : false,
                            "id" : "pbContainer",
                            "rows" : [
                              [
                                {
                                  "type" : "component",
                                  "dimension" : {
                                    "md" : 12,
                                    "sm" : 12,
                                    "xs" : 12,
                                    "lg" : 12
                                  },
                                  "propertyValues" : {
                                    "labelHidden" : {
                                      "type" : "constant",
                                      "value" : false
                                    },
                                    "hidden" : {
                                      "type" : "constant",
                                      "value" : false
                                    },
                                    "labelPosition" : {
                                      "type" : "constant",
                                      "value" : "top"
                                    },
                                    "cssClasses" : {
                                      "type" : "constant",
                                      "value" : ""
                                    },
                                    "labelWidth" : {
                                      "type" : "constant",
                                      "value" : 4
                                    },
                                    "label" : {
                                      "type" : "interpolation",
                                      "value" : "Instrukcije"
                                    },
                                    "placeholder" : {
                                      "type" : "constant",
                                      "value" : "Browse to upload a new file..."
                                    },
                                    "dimension" : {
                                      "type" : "constant",
                                      "value" : 12
                                    },
                                    "value" : {
                                      "type" : "variable",
                                      "value" : "$item.instrukcije"
                                    },
                                    "required" : {
                                      "type" : "constant",
                                      "value" : true
                                    },
                                    "url" : {
                                      "type" : "constant",
                                      "value" : "../API/formFileUpload"
                                    }
                                  },
                                  "reference" : "ce0ec91f-61a5-416a-8e3f-138cddc5788c",
                                  "hasValidationError" : false,
                                  "id" : "pbUpload",
                                  "description" : ""
                                }
                              ]
                            ]
                          }
                        ],
                        [
                          {
                            "type" : "component",
                            "dimension" : {
                              "md" : 12,
                              "sm" : 12,
                              "xs" : 12,
                              "lg" : 12
                            },
                            "propertyValues" : {
                              "removeItem" : {
                                "type" : "variable",
                                "value" : "$item"
                              },
                              "hidden" : {
                                "type" : "constant",
                                "value" : false
                              },
                              "cssClasses" : {
                                "type" : "constant",
                                "value" : ""
                              },
                              "buttonStyle" : {
                                "type" : "constant",
                                "value" : "danger"
                              },
                              "label" : {
                                "type" : "interpolation",
                                "value" : "<span class=\"glyphicon glyphicon-remove\"></span>"
                              },
                              "dataToSend" : {
                                "type" : "expression"
                              },
                              "labelHidden" : {
                                "type" : "constant",
                                "value" : false
                              },
                              "collectionPosition" : {
                                "type" : "constant",
                                "value" : "Item"
                              },
                              "targetUrlOnSuccess" : {
                                "type" : "interpolation"
                              },
                              "action" : {
                                "type" : "constant",
                                "value" : "Remove from collection"
                              },
                              "collectionToModify" : {
                                "type" : "variable",
                                "value" : "$collection"
                              },
                              "valueToAdd" : {
                                "type" : "expression"
                              },
                              "disabled" : {
                                "type" : "constant",
                                "value" : false
                              },
                              "alignment" : {
                                "type" : "constant",
                                "value" : "right"
                              },
                              "dimension" : {
                                "type" : "constant",
                                "value" : 12
                              }
                            },
                            "reference" : "0aca1b3e-0f2e-489b-9293-6849a5670093",
                            "hasValidationError" : false,
                            "id" : "pbButton",
                            "description" : ""
                          }
                        ]
                      ]
                    }
                  ],
                  [
                    {
                      "type" : "component",
                      "dimension" : {
                        "md" : 12,
                        "sm" : 12,
                        "xs" : 12,
                        "lg" : 12
                      },
                      "propertyValues" : {
                        "removeItem" : {
                          "type" : "variable"
                        },
                        "hidden" : {
                          "type" : "constant",
                          "value" : false
                        },
                        "cssClasses" : {
                          "type" : "constant",
                          "value" : ""
                        },
                        "buttonStyle" : {
                          "type" : "constant",
                          "value" : "primary"
                        },
                        "label" : {
                          "type" : "interpolation",
                          "value" : "<span class=\"glyphicon glyphicon-plus\"></span> Add StavkaZahtevaZaKodifikaciju"
                        },
                        "dataToSend" : {
                          "type" : "expression"
                        },
                        "labelHidden" : {
                          "type" : "constant",
                          "value" : false
                        },
                        "collectionPosition" : {
                          "type" : "constant"
                        },
                        "targetUrlOnSuccess" : {
                          "type" : "interpolation"
                        },
                        "action" : {
                          "type" : "constant",
                          "value" : "Add to collection"
                        },
                        "collectionToModify" : {
                          "type" : "variable",
                          "value" : "formInput.zahtevZaKodifikacijuInput.stavke"
                        },
                        "valueToAdd" : {
                          "type" : "expression",
                          "value" : "{\r\n  \"word_zakona\" : null,\r\n  \"skeniran_potpisan_zakon\" : null,\r\n  \"instrukcije\" : null\r\n}"
                        },
                        "disabled" : {
                          "type" : "constant",
                          "value" : false
                        },
                        "alignment" : {
                          "type" : "constant",
                          "value" : "left"
                        },
                        "dimension" : {
                          "type" : "constant",
                          "value" : 12
                        }
                      },
                      "reference" : "2a092af2-84d5-4adf-95a3-5a07521299f9",
                      "hasValidationError" : false,
                      "id" : "pbButton",
                      "description" : ""
                    }
                  ]
                ]
              }
            ],
            [
              {
                "type" : "component",
                "dimension" : {
                  "md" : 12,
                  "sm" : 12,
                  "xs" : 12,
                  "lg" : 12
                },
                "propertyValues" : {
                  "removeItem" : {
                    "type" : "variable"
                  },
                  "hidden" : {
                    "type" : "constant",
                    "value" : false
                  },
                  "cssClasses" : {
                    "type" : "constant",
                    "value" : ""
                  },
                  "buttonStyle" : {
                    "type" : "constant",
                    "value" : "primary"
                  },
                  "label" : {
                    "type" : "interpolation",
                    "value" : "Submit"
                  },
                  "dataToSend" : {
                    "type" : "expression",
                    "value" : "formOutput"
                  },
                  "dataFromError" : {
                    "type" : "variable",
                    "value" : "formOutput._submitError"
                  },
                  "labelHidden" : {
                    "type" : "constant",
                    "value" : false
                  },
                  "collectionPosition" : {
                    "type" : "constant"
                  },
                  "targetUrlOnSuccess" : {
                    "type" : "interpolation",
                    "value" : "/bonita"
                  },
                  "action" : {
                    "type" : "constant",
                    "value" : "Start process"
                  },
                  "collectionToModify" : {
                    "type" : "variable"
                  },
                  "valueToAdd" : {
                    "type" : "expression"
                  },
                  "disabled" : {
                    "type" : "expression",
                    "value" : "$form.$invalid"
                  },
                  "alignment" : {
                    "type" : "constant",
                    "value" : "center"
                  },
                  "dimension" : {
                    "type" : "constant",
                    "value" : 12
                  }
                },
                "reference" : "9fa4204f-536e-4d04-b684-a63c8869d8e8",
                "hasValidationError" : false,
                "id" : "pbButton",
                "description" : ""
              }
            ],
            [
              {
                "type" : "component",
                "dimension" : {
                  "md" : 12,
                  "sm" : 12,
                  "xs" : 12,
                  "lg" : 12
                },
                "propertyValues" : {
                  "allowHTML" : {
                    "type" : "constant",
                    "value" : true
                  },
                  "allowHtml" : {
                    "type" : "constant",
                    "value" : true
                  },
                  "labelHidden" : {
                    "type" : "constant",
                    "value" : true
                  },
                  "hidden" : {
                    "type" : "expression",
                    "value" : "!formOutput._submitError.message"
                  },
                  "cssClasses" : {
                    "type" : "constant",
                    "value" : "alert alert-danger col-lg-6 col-lg-offset-3"
                  },
                  "label" : {
                    "type" : "interpolation"
                  },
                  "text" : {
                    "type" : "interpolation",
                    "value" : "<strong>Debug message</strong>\n<br/>\n{{formOutput._submitError.message}}\n{{submit_errors_list}}"
                  },
                  "alignment" : {
                    "type" : "constant",
                    "value" : "left"
                  },
                  "dimension" : {
                    "type" : "constant",
                    "value" : 12
                  }
                },
                "reference" : "d4756e24-8f43-4877-a7ea-687f2357a0bd",
                "hasValidationError" : false,
                "id" : "pbText",
                "description" : ""
              }
            ]
          ]
        }
      }
    ]
  ],
  "assets" : [
    {
      "id" : "267b3015-556b-43d6-9a97-5f7001e94274",
      "name" : "style.css",
      "type" : "css",
      "order" : 0,
      "external" : false
    },
    {
      "id" : "e85da555-b3ff-47f1-bf7e-63bf499128f2",
      "name" : "localization.json",
      "type" : "json",
      "order" : 0,
      "external" : false
    }
  ],
  "inactiveAssets" : [ ],
  "variables" : {
    "formInput" : {
      "type" : "json",
      "value" : [
        "{\r",
        "  \"zahtevZaKodifikacijuInput\" : {\r",
        "    \"stavke\" : [ ]\r",
        "  }\r",
        "}"
      ],
      "exposed" : false
    },
    "stavkaZahtevaZaKodifikaciju_query" : {
      "type" : "url",
      "value" : [
        "../API/bdm/businessData/paket.kodifikacijaZakona.StavkaZahtevaZaKodifikaciju?q=find&p=0&c=99"
      ],
      "exposed" : false
    },
    "submit_errors_list" : {
      "type" : "expression",
      "value" : [
        "if($data.formOutput && $data.formOutput._submitError && $data.formOutput._submitError.explanations){",
        "\tconst liElements = $data.formOutput._submitError.explanations",
        "\t\t.filter(cause => cause !== null)",
        "\t\t.map(cause => \"<li>\" + cause + \"</li>\")",
        "\t\t.join('');",
        "\tif(liElements){",
        "\t\treturn \"<ul>\" + liElements + \"</ul>\";",
        "\t}",
        "}"
      ],
      "exposed" : false
    },
    "formOutput" : {
      "type" : "expression",
      "value" : [
        "return {",
        "\tzahtevZaKodifikacijuInput: $data.formInput.zahtevZaKodifikacijuInput",
        "}"
      ],
      "exposed" : false
    }
  },
  "hasValidationError" : false,
  "uuid" : "a9e0306e-d961-4efb-9e42-15383b4e54fa",
  "type" : "form",
  "description" : "Page generated with Bonita UI designer"
}