{
  "modelVersion" : "2.2",
  "id" : "newForm17",
  "name" : "newForm17",
  "lastUpdate" : 1701542303187,
  "rows" : [
    [
      {
        "type" : "container",
        "dimension" : {
          "xs" : 12
        },
        "propertyValues" : { },
        "reference" : "8e99ad48-e237-40a2-9b90-eaef61fb7877",
        "hasValidationError" : false,
        "id" : "pbContainer",
        "rows" : [
          [
            {
              "type" : "component",
              "dimension" : {
                "md" : 12,
                "sm" : 12,
                "xs" : 12,
                "lg" : 12
              },
              "propertyValues" : {
                "hidden" : {
                  "type" : "constant",
                  "value" : false
                },
                "level" : {
                  "type" : "constant",
                  "value" : "Level 1"
                },
                "cssClasses" : {
                  "type" : "constant",
                  "value" : ""
                },
                "text" : {
                  "type" : "interpolation",
                  "value" : "{{ task.displayName }}"
                },
                "alignment" : {
                  "type" : "constant",
                  "value" : "center"
                },
                "dimension" : {
                  "type" : "constant",
                  "value" : 12
                }
              },
              "reference" : "6d2cb762-7c05-463f-9e45-3dd85b546831",
              "hasValidationError" : false,
              "id" : "pbTitle",
              "description" : ""
            }
          ],
          [
            {
              "type" : "component",
              "dimension" : {
                "md" : 12,
                "sm" : 12,
                "xs" : 12,
                "lg" : 12
              },
              "propertyValues" : {
                "allowHtml" : {
                  "type" : "constant",
                  "value" : true
                },
                "labelHidden" : {
                  "type" : "constant",
                  "value" : true
                },
                "hidden" : {
                  "type" : "constant",
                  "value" : false
                },
                "cssClasses" : {
                  "type" : "constant",
                  "value" : ""
                },
                "label" : {
                  "type" : "interpolation"
                },
                "text" : {
                  "type" : "interpolation",
                  "value" : "{{ task.displayDescription }}"
                },
                "alignment" : {
                  "type" : "constant",
                  "value" : "left"
                },
                "dimension" : {
                  "type" : "constant",
                  "value" : 12
                }
              },
              "reference" : "e04f2906-109e-4cd6-8cc6-ea46bb7e9af2",
              "hasValidationError" : false,
              "id" : "pbText",
              "description" : ""
            }
          ]
        ]
      }
    ],
    [
      {
        "type" : "formContainer",
        "dimension" : {
          "xs" : 12
        },
        "propertyValues" : { },
        "reference" : "a60054e6-4927-4924-8336-2a463b362bba",
        "hasValidationError" : false,
        "id" : "pbFormContainer",
        "container" : {
          "type" : "container",
          "dimension" : {
            "xs" : 12
          },
          "propertyValues" : { },
          "reference" : "1992c10c-c750-401c-9bff-20f634f00252",
          "hasValidationError" : false,
          "id" : "pbContainer",
          "rows" : [
            [
              {
                "type" : "component",
                "dimension" : {
                  "md" : 12,
                  "sm" : 12,
                  "xs" : 12,
                  "lg" : 12
                },
                "propertyValues" : {
                  "hidden" : {
                    "type" : "constant",
                    "value" : false
                  },
                  "level" : {
                    "type" : "constant",
                    "value" : "Level 4"
                  },
                  "cssClasses" : {
                    "type" : "constant",
                    "value" : ""
                  },
                  "text" : {
                    "type" : "interpolation",
                    "value" : "Zahtev Za Kodifikaciju"
                  },
                  "alignment" : {
                    "type" : "constant",
                    "value" : "left"
                  },
                  "dimension" : {
                    "type" : "constant",
                    "value" : 12
                  }
                },
                "reference" : "6d0550e8-d998-4c98-93d6-c893c8f84a77",
                "hasValidationError" : false,
                "id" : "pbTitle",
                "description" : ""
              }
            ],
            [
              {
                "type" : "container",
                "dimension" : {
                  "md" : 12,
                  "sm" : 12,
                  "xs" : 12,
                  "lg" : 12
                },
                "propertyValues" : {
                  "repeatedCollection" : {
                    "type" : "variable"
                  },
                  "hidden" : {
                    "type" : "constant",
                    "value" : false
                  },
                  "cssClasses" : {
                    "type" : "constant",
                    "value" : ""
                  },
                  "dimension" : {
                    "type" : "constant",
                    "value" : 12
                  }
                },
                "reference" : "7d05df9e-de7d-4361-b890-90af20aef1f5",
                "hasValidationError" : false,
                "id" : "pbContainer",
                "rows" : [
                  [
                    {
                      "type" : "component",
                      "dimension" : {
                        "md" : 12,
                        "sm" : 12,
                        "xs" : 12,
                        "lg" : 12
                      },
                      "propertyValues" : {
                        "hidden" : {
                          "type" : "constant",
                          "value" : false
                        },
                        "level" : {
                          "type" : "constant",
                          "value" : "Level 4"
                        },
                        "cssClasses" : {
                          "type" : "constant",
                          "value" : ""
                        },
                        "text" : {
                          "type" : "interpolation",
                          "value" : "Stavke"
                        },
                        "alignment" : {
                          "type" : "constant",
                          "value" : "left"
                        },
                        "dimension" : {
                          "type" : "constant",
                          "value" : 12
                        }
                      },
                      "reference" : "a26d4621-ebf0-4321-adce-e04850c02556",
                      "hasValidationError" : false,
                      "id" : "pbTitle",
                      "description" : ""
                    }
                  ],
                  [
                    {
                      "type" : "container",
                      "dimension" : {
                        "md" : 12,
                        "sm" : 12,
                        "xs" : 12,
                        "lg" : 12
                      },
                      "propertyValues" : {
                        "repeatedCollection" : {
                          "type" : "variable",
                          "value" : "zahtevZaKodifikaciju_stavke"
                        },
                        "hidden" : {
                          "type" : "constant",
                          "value" : false
                        },
                        "cssClasses" : {
                          "type" : "constant",
                          "value" : ""
                        },
                        "dimension" : {
                          "type" : "constant",
                          "value" : 12
                        }
                      },
                      "reference" : "e3dd91c4-6c1e-4a31-bf4e-d73c3364420a",
                      "hasValidationError" : false,
                      "id" : "pbContainer",
                      "rows" : [
                        [
                          {
                            "type" : "component",
                            "dimension" : {
                              "md" : 12,
                              "sm" : 12,
                              "xs" : 12,
                              "lg" : 12
                            },
                            "propertyValues" : {
                              "labelHidden" : {
                                "type" : "constant",
                                "value" : false
                              },
                              "hidden" : {
                                "type" : "constant",
                                "value" : false
                              },
                              "labelPosition" : {
                                "type" : "constant",
                                "value" : "top"
                              },
                              "cssClasses" : {
                                "type" : "constant",
                                "value" : ""
                              },
                              "availableValues" : {
                                "type" : "expression",
                                "value" : "stavkaZahtevaZaKodifikaciju_query"
                              },
                              "labelWidth" : {
                                "type" : "constant",
                                "value" : 1
                              },
                              "label" : {
                                "type" : "interpolation",
                                "value" : "Stavke"
                              },
                              "placeholder" : {
                                "type" : "constant",
                                "value" : "Select a Stavke"
                              },
                              "dimension" : {
                                "type" : "constant",
                                "value" : 12
                              },
                              "value" : {
                                "type" : "variable",
                                "value" : "$item"
                              },
                              "required" : {
                                "type" : "constant",
                                "value" : true
                              }
                            },
                            "reference" : "a096f631-d243-45e2-a4a4-b3591ac1a67b",
                            "hasValidationError" : false,
                            "id" : "pbSelect",
                            "description" : ""
                          }
                        ],
                        [
                          {
                            "type" : "component",
                            "dimension" : {
                              "md" : 12,
                              "sm" : 12,
                              "xs" : 12,
                              "lg" : 12
                            },
                            "propertyValues" : {
                              "labelHidden" : {
                                "type" : "constant",
                                "value" : false
                              },
                              "hidden" : {
                                "type" : "constant",
                                "value" : false
                              },
                              "labelPosition" : {
                                "type" : "constant",
                                "value" : "top"
                              },
                              "cssClasses" : {
                                "type" : "constant",
                                "value" : ""
                              },
                              "labelWidth" : {
                                "type" : "constant",
                                "value" : 1
                              },
                              "readOnly" : {
                                "type" : "constant",
                                "value" : false
                              },
                              "label" : {
                                "type" : "interpolation",
                                "value" : "Dokument Zakona"
                              },
                              "placeholder" : {
                                "type" : "constant"
                              },
                              "type" : {
                                "type" : "constant",
                                "value" : "text"
                              },
                              "dimension" : {
                                "type" : "constant",
                                "value" : 12
                              },
                              "value" : {
                                "type" : "variable",
                                "value" : "$item.dokumentZakona"
                              },
                              "required" : {
                                "type" : "constant",
                                "value" : true
                              }
                            },
                            "reference" : "6f86a34f-3776-43bd-bc20-fb60b2f6f114",
                            "hasValidationError" : false,
                            "id" : "pbInput",
                            "description" : ""
                          }
                        ],
                        [
                          {
                            "type" : "component",
                            "dimension" : {
                              "md" : 12,
                              "sm" : 12,
                              "xs" : 12,
                              "lg" : 12
                            },
                            "propertyValues" : {
                              "labelHidden" : {
                                "type" : "constant",
                                "value" : false
                              },
                              "hidden" : {
                                "type" : "constant",
                                "value" : false
                              },
                              "labelPosition" : {
                                "type" : "constant",
                                "value" : "top"
                              },
                              "cssClasses" : {
                                "type" : "constant",
                                "value" : ""
                              },
                              "labelWidth" : {
                                "type" : "constant",
                                "value" : 1
                              },
                              "readOnly" : {
                                "type" : "constant",
                                "value" : false
                              },
                              "label" : {
                                "type" : "interpolation",
                                "value" : "Instrukcije Za Kodifikaciju"
                              },
                              "placeholder" : {
                                "type" : "constant"
                              },
                              "type" : {
                                "type" : "constant",
                                "value" : "text"
                              },
                              "dimension" : {
                                "type" : "constant",
                                "value" : 12
                              },
                              "value" : {
                                "type" : "variable",
                                "value" : "$item.instrukcijeZaKodifikaciju"
                              },
                              "required" : {
                                "type" : "constant",
                                "value" : false
                              }
                            },
                            "reference" : "e59e3b60-4c0a-42eb-9918-4057c28b5371",
                            "hasValidationError" : false,
                            "id" : "pbInput",
                            "description" : ""
                          }
                        ],
                        [
                          {
                            "type" : "component",
                            "dimension" : {
                              "md" : 12,
                              "sm" : 12,
                              "xs" : 12,
                              "lg" : 12
                            },
                            "propertyValues" : {
                              "labelHidden" : {
                                "type" : "constant",
                                "value" : false
                              },
                              "hidden" : {
                                "type" : "constant",
                                "value" : false
                              },
                              "labelPosition" : {
                                "type" : "constant",
                                "value" : "top"
                              },
                              "cssClasses" : {
                                "type" : "constant",
                                "value" : ""
                              },
                              "labelWidth" : {
                                "type" : "constant",
                                "value" : 1
                              },
                              "readOnly" : {
                                "type" : "constant",
                                "value" : false
                              },
                              "label" : {
                                "type" : "interpolation",
                                "value" : "Skeniran Potpisan Zakon"
                              },
                              "placeholder" : {
                                "type" : "constant"
                              },
                              "type" : {
                                "type" : "constant",
                                "value" : "text"
                              },
                              "dimension" : {
                                "type" : "constant",
                                "value" : 12
                              },
                              "value" : {
                                "type" : "variable",
                                "value" : "$item.skeniranPotpisanZakon"
                              },
                              "required" : {
                                "type" : "constant",
                                "value" : false
                              }
                            },
                            "reference" : "c9ee85f8-0465-4daa-bc7d-5b558428cf4b",
                            "hasValidationError" : false,
                            "id" : "pbInput",
                            "description" : ""
                          }
                        ],
                        [
                          {
                            "type" : "component",
                            "dimension" : {
                              "md" : 12,
                              "sm" : 12,
                              "xs" : 12,
                              "lg" : 12
                            },
                            "propertyValues" : {
                              "labelHidden" : {
                                "type" : "constant",
                                "value" : false
                              },
                              "hidden" : {
                                "type" : "expression",
                                "value" : "!$item.odobrenOdStraneAdvokataZaReviziju"
                              },
                              "cssClasses" : {
                                "type" : "constant",
                                "value" : ""
                              },
                              "disabled" : {
                                "type" : "constant",
                                "value" : true
                              },
                              "label" : {
                                "type" : "interpolation",
                                "value" : "Odobren Od Strane Advokata Za Reviziju"
                              },
                              "dimension" : {
                                "type" : "constant",
                                "value" : 12
                              },
                              "value" : {
                                "type" : "variable",
                                "value" : "$item.odobrenOdStraneAdvokataZaReviziju"
                              }
                            },
                            "reference" : "906e6ac3-9193-495e-9c2f-63c07b465dde",
                            "hasValidationError" : false,
                            "id" : "pbCheckbox",
                            "description" : ""
                          }
                        ],
                        [
                          {
                            "type" : "component",
                            "dimension" : {
                              "md" : 12,
                              "sm" : 12,
                              "xs" : 12,
                              "lg" : 12
                            },
                            "propertyValues" : {
                              "labelHidden" : {
                                "type" : "constant",
                                "value" : false
                              },
                              "hidden" : {
                                "type" : "expression",
                                "value" : "!$item.odobrenOdStraneVlade"
                              },
                              "cssClasses" : {
                                "type" : "constant",
                                "value" : ""
                              },
                              "disabled" : {
                                "type" : "constant",
                                "value" : true
                              },
                              "label" : {
                                "type" : "interpolation",
                                "value" : "Odobren Od Strane Vlade"
                              },
                              "dimension" : {
                                "type" : "constant",
                                "value" : 12
                              },
                              "value" : {
                                "type" : "variable",
                                "value" : "$item.odobrenOdStraneVlade"
                              }
                            },
                            "reference" : "ac08e33f-2c40-4072-b079-b380e3065604",
                            "hasValidationError" : false,
                            "id" : "pbCheckbox",
                            "description" : ""
                          }
                        ],
                        [
                          {
                            "type" : "component",
                            "dimension" : {
                              "md" : 12,
                              "sm" : 12,
                              "xs" : 12,
                              "lg" : 12
                            },
                            "propertyValues" : {
                              "hidden" : {
                                "type" : "constant",
                                "value" : false
                              },
                              "level" : {
                                "type" : "constant",
                                "value" : "Level 4"
                              },
                              "cssClasses" : {
                                "type" : "constant",
                                "value" : ""
                              },
                              "text" : {
                                "type" : "interpolation",
                                "value" : "Zatrazene Izmene"
                              },
                              "alignment" : {
                                "type" : "constant",
                                "value" : "left"
                              },
                              "dimension" : {
                                "type" : "constant",
                                "value" : 12
                              }
                            },
                            "reference" : "b8dccab6-e870-4098-9a9c-62b2198db761",
                            "hasValidationError" : false,
                            "id" : "pbTitle",
                            "description" : ""
                          }
                        ],
                        [
                          {
                            "type" : "container",
                            "dimension" : {
                              "md" : 12,
                              "sm" : 12,
                              "xs" : 12,
                              "lg" : 12
                            },
                            "propertyValues" : {
                              "repeatedCollection" : {
                                "type" : "variable",
                                "value" : "$item.zatrazeneIzmene"
                              },
                              "hidden" : {
                                "type" : "constant",
                                "value" : false
                              },
                              "cssClasses" : {
                                "type" : "constant",
                                "value" : ""
                              },
                              "dimension" : {
                                "type" : "constant",
                                "value" : 12
                              }
                            },
                            "reference" : "0195a386-b19b-4e14-a6e2-9befecb208db",
                            "hasValidationError" : false,
                            "id" : "pbContainer",
                            "rows" : [
                              [
                                {
                                  "type" : "component",
                                  "dimension" : {
                                    "md" : 12,
                                    "sm" : 12,
                                    "xs" : 12,
                                    "lg" : 12
                                  },
                                  "propertyValues" : {
                                    "allowHtml" : {
                                      "type" : "constant",
                                      "value" : true
                                    },
                                    "labelHidden" : {
                                      "type" : "constant",
                                      "value" : false
                                    },
                                    "hidden" : {
                                      "type" : "expression",
                                      "value" : "!$item.zatrazeneIzmene"
                                    },
                                    "cssClasses" : {
                                      "type" : "constant",
                                      "value" : ""
                                    },
                                    "label" : {
                                      "type" : "interpolation",
                                      "value" : "Zatrazene Izmene"
                                    },
                                    "text" : {
                                      "type" : "interpolation",
                                      "value" : "{{$item.zatrazeneIzmene}}"
                                    },
                                    "alignment" : {
                                      "type" : "constant",
                                      "value" : "left"
                                    },
                                    "dimension" : {
                                      "type" : "constant",
                                      "value" : 12
                                    }
                                  },
                                  "reference" : "76fdcbce-176c-44cc-81aa-6eacd82d0040",
                                  "hasValidationError" : false,
                                  "id" : "pbText",
                                  "description" : ""
                                }
                              ]
                            ]
                          }
                        ],
                        [
                          {
                            "type" : "component",
                            "dimension" : {
                              "md" : 12,
                              "sm" : 12,
                              "xs" : 12,
                              "lg" : 12
                            },
                            "propertyValues" : {
                              "labelHidden" : {
                                "type" : "constant",
                                "value" : false
                              },
                              "hidden" : {
                                "type" : "expression",
                                "value" : "!$item.potrebnaPojasnjenja"
                              },
                              "cssClasses" : {
                                "type" : "constant",
                                "value" : ""
                              },
                              "disabled" : {
                                "type" : "constant",
                                "value" : true
                              },
                              "label" : {
                                "type" : "interpolation",
                                "value" : "Potrebna Pojasnjenja"
                              },
                              "dimension" : {
                                "type" : "constant",
                                "value" : 12
                              },
                              "value" : {
                                "type" : "variable",
                                "value" : "$item.potrebnaPojasnjenja"
                              }
                            },
                            "reference" : "171fb501-0bee-4e48-b4f2-7b4c04d71538",
                            "hasValidationError" : false,
                            "id" : "pbCheckbox",
                            "description" : ""
                          }
                        ],
                        [
                          {
                            "type" : "component",
                            "dimension" : {
                              "md" : 12,
                              "sm" : 12,
                              "xs" : 12,
                              "lg" : 12
                            },
                            "propertyValues" : {
                              "removeItem" : {
                                "type" : "variable",
                                "value" : "$item"
                              },
                              "hidden" : {
                                "type" : "constant",
                                "value" : false
                              },
                              "cssClasses" : {
                                "type" : "constant",
                                "value" : ""
                              },
                              "buttonStyle" : {
                                "type" : "constant",
                                "value" : "danger"
                              },
                              "label" : {
                                "type" : "interpolation",
                                "value" : "<span class=\"glyphicon glyphicon-remove\"></span>"
                              },
                              "dataToSend" : {
                                "type" : "expression"
                              },
                              "labelHidden" : {
                                "type" : "constant",
                                "value" : false
                              },
                              "collectionPosition" : {
                                "type" : "constant",
                                "value" : "Item"
                              },
                              "targetUrlOnSuccess" : {
                                "type" : "interpolation"
                              },
                              "action" : {
                                "type" : "constant",
                                "value" : "Remove from collection"
                              },
                              "collectionToModify" : {
                                "type" : "variable",
                                "value" : "$collection"
                              },
                              "valueToAdd" : {
                                "type" : "expression"
                              },
                              "disabled" : {
                                "type" : "constant",
                                "value" : false
                              },
                              "alignment" : {
                                "type" : "constant",
                                "value" : "right"
                              },
                              "dimension" : {
                                "type" : "constant",
                                "value" : 12
                              }
                            },
                            "reference" : "10e247e1-b5e5-4f5d-b29e-bc2b5bebfcbb",
                            "hasValidationError" : false,
                            "id" : "pbButton",
                            "description" : ""
                          }
                        ]
                      ]
                    }
                  ],
                  [
                    {
                      "type" : "component",
                      "dimension" : {
                        "md" : 12,
                        "sm" : 12,
                        "xs" : 12,
                        "lg" : 12
                      },
                      "propertyValues" : {
                        "removeItem" : {
                          "type" : "variable"
                        },
                        "hidden" : {
                          "type" : "constant",
                          "value" : false
                        },
                        "cssClasses" : {
                          "type" : "constant",
                          "value" : ""
                        },
                        "buttonStyle" : {
                          "type" : "constant",
                          "value" : "primary"
                        },
                        "label" : {
                          "type" : "interpolation",
                          "value" : "<span class=\"glyphicon glyphicon-plus\"></span> Add StavkaZahtevaZaKodifikaciju"
                        },
                        "dataToSend" : {
                          "type" : "expression"
                        },
                        "labelHidden" : {
                          "type" : "constant",
                          "value" : false
                        },
                        "collectionPosition" : {
                          "type" : "constant"
                        },
                        "targetUrlOnSuccess" : {
                          "type" : "interpolation"
                        },
                        "action" : {
                          "type" : "constant",
                          "value" : "Add to collection"
                        },
                        "collectionToModify" : {
                          "type" : "variable",
                          "value" : "zahtevZaKodifikaciju_stavke"
                        },
                        "valueToAdd" : {
                          "type" : "expression",
                          "value" : "{\r\n  \"persistenceId_string\" : \"\",\r\n  \"dokumentZakona\" : \"\",\r\n  \"instrukcijeZaKodifikaciju\" : \"\",\r\n  \"skeniranPotpisanZakon\" : \"\",\r\n  \"odobrenOdStraneAdvokataZaReviziju\" : false,\r\n  \"odobrenOdStraneVlade\" : false,\r\n  \"zatrazeneIzmene\" : [ ],\r\n  \"potrebnaPojasnjenja\" : false\r\n}"
                        },
                        "disabled" : {
                          "type" : "constant",
                          "value" : false
                        },
                        "alignment" : {
                          "type" : "constant",
                          "value" : "left"
                        },
                        "dimension" : {
                          "type" : "constant",
                          "value" : 12
                        }
                      },
                      "reference" : "72f81588-c41d-416f-ace3-c095136b2b82",
                      "hasValidationError" : false,
                      "id" : "pbButton",
                      "description" : ""
                    }
                  ],
                  [
                    {
                      "type" : "component",
                      "dimension" : {
                        "md" : 12,
                        "sm" : 12,
                        "xs" : 12,
                        "lg" : 12
                      },
                      "propertyValues" : {
                        "hidden" : {
                          "type" : "constant",
                          "value" : false
                        },
                        "level" : {
                          "type" : "constant",
                          "value" : "Level 4"
                        },
                        "cssClasses" : {
                          "type" : "constant",
                          "value" : ""
                        },
                        "text" : {
                          "type" : "interpolation",
                          "value" : "Status"
                        },
                        "alignment" : {
                          "type" : "constant",
                          "value" : "left"
                        },
                        "dimension" : {
                          "type" : "constant",
                          "value" : 12
                        }
                      },
                      "reference" : "f5ce5c42-ea99-4290-a756-58e09cecada6",
                      "hasValidationError" : false,
                      "id" : "pbTitle",
                      "description" : ""
                    }
                  ],
                  [
                    {
                      "type" : "container",
                      "dimension" : {
                        "md" : 12,
                        "sm" : 12,
                        "xs" : 12,
                        "lg" : 12
                      },
                      "propertyValues" : {
                        "repeatedCollection" : {
                          "type" : "variable"
                        },
                        "hidden" : {
                          "type" : "constant",
                          "value" : false
                        },
                        "cssClasses" : {
                          "type" : "constant",
                          "value" : ""
                        },
                        "dimension" : {
                          "type" : "constant",
                          "value" : 12
                        }
                      },
                      "reference" : "55e097e7-c89c-4cf0-991f-6ba56ebca357",
                      "hasValidationError" : false,
                      "id" : "pbContainer",
                      "rows" : [
                        [
                          {
                            "type" : "component",
                            "dimension" : {
                              "md" : 12,
                              "sm" : 12,
                              "xs" : 12,
                              "lg" : 12
                            },
                            "propertyValues" : {
                              "labelHidden" : {
                                "type" : "constant",
                                "value" : false
                              },
                              "hidden" : {
                                "type" : "constant",
                                "value" : false
                              },
                              "labelPosition" : {
                                "type" : "constant",
                                "value" : "top"
                              },
                              "cssClasses" : {
                                "type" : "constant",
                                "value" : ""
                              },
                              "availableValues" : {
                                "type" : "expression",
                                "value" : "statusZahtevaZaKodifikaciju_query"
                              },
                              "labelWidth" : {
                                "type" : "constant",
                                "value" : 1
                              },
                              "label" : {
                                "type" : "interpolation",
                                "value" : "Status"
                              },
                              "placeholder" : {
                                "type" : "constant",
                                "value" : "Select a Status"
                              },
                              "dimension" : {
                                "type" : "constant",
                                "value" : 12
                              },
                              "value" : {
                                "type" : "variable",
                                "value" : "zahtevZaKodifikaciju_status"
                              },
                              "required" : {
                                "type" : "constant",
                                "value" : true
                              }
                            },
                            "reference" : "8db11620-d4d5-4813-b502-cd4e47d0e6df",
                            "hasValidationError" : false,
                            "id" : "pbSelect",
                            "description" : ""
                          }
                        ],
                        [
                          {
                            "type" : "component",
                            "dimension" : {
                              "md" : 12,
                              "sm" : 12,
                              "xs" : 12,
                              "lg" : 12
                            },
                            "propertyValues" : {
                              "labelHidden" : {
                                "type" : "constant",
                                "value" : false
                              },
                              "hidden" : {
                                "type" : "constant",
                                "value" : false
                              },
                              "labelPosition" : {
                                "type" : "constant",
                                "value" : "top"
                              },
                              "cssClasses" : {
                                "type" : "constant",
                                "value" : ""
                              },
                              "labelWidth" : {
                                "type" : "constant",
                                "value" : 1
                              },
                              "readOnly" : {
                                "type" : "constant",
                                "value" : false
                              },
                              "label" : {
                                "type" : "interpolation",
                                "value" : "Status"
                              },
                              "placeholder" : {
                                "type" : "constant"
                              },
                              "type" : {
                                "type" : "constant",
                                "value" : "text"
                              },
                              "dimension" : {
                                "type" : "constant",
                                "value" : 12
                              },
                              "value" : {
                                "type" : "variable",
                                "value" : "zahtevZaKodifikaciju_status.status"
                              },
                              "required" : {
                                "type" : "constant",
                                "value" : true
                              }
                            },
                            "reference" : "bea4892b-57b0-44e9-9619-05f379a8399d",
                            "hasValidationError" : false,
                            "id" : "pbInput",
                            "description" : ""
                          }
                        ]
                      ]
                    }
                  ],
                  [
                    {
                      "type" : "component",
                      "dimension" : {
                        "md" : 12,
                        "sm" : 12,
                        "xs" : 12,
                        "lg" : 12
                      },
                      "propertyValues" : {
                        "allowHtml" : {
                          "type" : "constant",
                          "value" : true
                        },
                        "labelHidden" : {
                          "type" : "constant",
                          "value" : false
                        },
                        "hidden" : {
                          "type" : "expression",
                          "value" : "!zahtevZaKodifikaciju.preostaloVremeZaIzvrsavanje"
                        },
                        "cssClasses" : {
                          "type" : "constant",
                          "value" : ""
                        },
                        "label" : {
                          "type" : "interpolation",
                          "value" : "Preostalo Vreme Za Izvrsavanje"
                        },
                        "text" : {
                          "type" : "interpolation",
                          "value" : "{{zahtevZaKodifikaciju.preostaloVremeZaIzvrsavanje}}"
                        },
                        "alignment" : {
                          "type" : "constant",
                          "value" : "left"
                        },
                        "dimension" : {
                          "type" : "constant",
                          "value" : 12
                        }
                      },
                      "reference" : "87cafb7f-1efd-49b6-a551-71318ff9bb7f",
                      "hasValidationError" : false,
                      "id" : "pbText",
                      "description" : ""
                    }
                  ],
                  [
                    {
                      "type" : "component",
                      "dimension" : {
                        "md" : 12,
                        "sm" : 12,
                        "xs" : 12,
                        "lg" : 12
                      },
                      "propertyValues" : {
                        "hidden" : {
                          "type" : "constant",
                          "value" : false
                        },
                        "dateFormat" : {
                          "type" : "constant",
                          "value" : "MM/dd/yyyy"
                        },
                        "cssClasses" : {
                          "type" : "constant",
                          "value" : ""
                        },
                        "labelWidth" : {
                          "type" : "constant",
                          "value" : 1
                        },
                        "readOnly" : {
                          "type" : "constant",
                          "value" : false
                        },
                        "label" : {
                          "type" : "interpolation",
                          "value" : "Datum Iniciranja"
                        },
                        "type" : {
                          "type" : "constant"
                        },
                        "required" : {
                          "type" : "constant",
                          "value" : true
                        },
                        "todayLabel" : {
                          "type" : "constant",
                          "value" : "Today"
                        },
                        "labelHidden" : {
                          "type" : "constant",
                          "value" : false
                        },
                        "showToday" : {
                          "type" : "constant",
                          "value" : true
                        },
                        "labelPosition" : {
                          "type" : "constant",
                          "value" : "top"
                        },
                        "placeholder" : {
                          "type" : "constant",
                          "value" : "Enter a date (mm/dd/yyyy)"
                        },
                        "dimension" : {
                          "type" : "constant",
                          "value" : 12
                        },
                        "value" : {
                          "type" : "variable",
                          "value" : "zahtevZaKodifikaciju.datumIniciranja"
                        }
                      },
                      "reference" : "49edf6ed-f2db-45d2-a734-6b1cdae59ffe",
                      "hasValidationError" : false,
                      "id" : "pbDatePicker",
                      "description" : ""
                    }
                  ]
                ]
              }
            ],
            [
              {
                "type" : "component",
                "dimension" : {
                  "md" : 12,
                  "sm" : 12,
                  "xs" : 12,
                  "lg" : 12
                },
                "propertyValues" : {
                  "removeItem" : {
                    "type" : "variable"
                  },
                  "hidden" : {
                    "type" : "constant",
                    "value" : false
                  },
                  "cssClasses" : {
                    "type" : "constant",
                    "value" : ""
                  },
                  "buttonStyle" : {
                    "type" : "constant",
                    "value" : "primary"
                  },
                  "label" : {
                    "type" : "interpolation",
                    "value" : "Submit"
                  },
                  "dataToSend" : {
                    "type" : "expression",
                    "value" : "formOutput"
                  },
                  "dataFromError" : {
                    "type" : "variable",
                    "value" : "formOutput._submitError"
                  },
                  "labelHidden" : {
                    "type" : "constant",
                    "value" : false
                  },
                  "collectionPosition" : {
                    "type" : "constant"
                  },
                  "targetUrlOnSuccess" : {
                    "type" : "interpolation",
                    "value" : "/bonita"
                  },
                  "action" : {
                    "type" : "constant",
                    "value" : "Submit task"
                  },
                  "collectionToModify" : {
                    "type" : "variable"
                  },
                  "valueToAdd" : {
                    "type" : "expression"
                  },
                  "disabled" : {
                    "type" : "expression",
                    "value" : "$form.$invalid"
                  },
                  "alignment" : {
                    "type" : "constant",
                    "value" : "center"
                  },
                  "dimension" : {
                    "type" : "constant",
                    "value" : 12
                  }
                },
                "reference" : "93f28bbf-5712-4889-958a-e9caef01b396",
                "hasValidationError" : false,
                "id" : "pbButton",
                "description" : ""
              }
            ],
            [
              {
                "type" : "component",
                "dimension" : {
                  "md" : 12,
                  "sm" : 12,
                  "xs" : 12,
                  "lg" : 12
                },
                "propertyValues" : {
                  "allowHTML" : {
                    "type" : "constant",
                    "value" : true
                  },
                  "allowHtml" : {
                    "type" : "constant",
                    "value" : true
                  },
                  "labelHidden" : {
                    "type" : "constant",
                    "value" : true
                  },
                  "hidden" : {
                    "type" : "expression",
                    "value" : "!formOutput._submitError.message"
                  },
                  "cssClasses" : {
                    "type" : "constant",
                    "value" : "alert alert-danger col-lg-6 col-lg-offset-3"
                  },
                  "label" : {
                    "type" : "interpolation"
                  },
                  "text" : {
                    "type" : "interpolation",
                    "value" : "<strong>Debug message</strong>\n<br/>\n{{formOutput._submitError.message}}\n{{submit_errors_list}}"
                  },
                  "alignment" : {
                    "type" : "constant",
                    "value" : "left"
                  },
                  "dimension" : {
                    "type" : "constant",
                    "value" : 12
                  }
                },
                "reference" : "93153033-5a20-4494-99b2-001b7e358bc1",
                "hasValidationError" : false,
                "id" : "pbText",
                "description" : ""
              }
            ]
          ]
        }
      }
    ]
  ],
  "assets" : [
    {
      "id" : "76028eed-c4dd-42b2-8e85-f41797bc2d57",
      "name" : "localization.json",
      "type" : "json",
      "order" : 0,
      "external" : false
    },
    {
      "id" : "296975a5-15d9-4e68-801f-c407af408c2e",
      "name" : "style.css",
      "type" : "css",
      "order" : 0,
      "external" : false
    }
  ],
  "inactiveAssets" : [ ],
  "variables" : {
    "task" : {
      "type" : "url",
      "value" : [
        "../API/bpm/userTask/{{taskId}}"
      ],
      "exposed" : false
    },
    "stavkaZahtevaZaKodifikaciju_query" : {
      "type" : "url",
      "value" : [
        "../API/bdm/businessData/paket.kodifikacijaZakona.StavkaZahtevaZaKodifikaciju?q=find&p=0&c=99"
      ],
      "exposed" : false
    },
    "submit_errors_list" : {
      "type" : "expression",
      "value" : [
        "if($data.formOutput && $data.formOutput._submitError && $data.formOutput._submitError.explanations){",
        "\tconst liElements = $data.formOutput._submitError.explanations",
        "\t\t.filter(cause => cause !== null)",
        "\t\t.map(cause => \"<li>\" + cause + \"</li>\")",
        "\t\t.join('');",
        "\tif(liElements){",
        "\t\treturn \"<ul>\" + liElements + \"</ul>\";",
        "\t}",
        "}"
      ],
      "exposed" : false
    },
    "statusZahtevaZaKodifikaciju_query" : {
      "type" : "url",
      "value" : [
        "../API/bdm/businessData/paket.kodifikacijaZakona.StatusZahtevaZaKodifikaciju?q=find&p=0&c=99"
      ],
      "exposed" : false
    },
    "formOutput" : {
      "type" : "expression",
      "value" : [
        "if( $data.zahtevZaKodifikaciju && $data.zahtevZaKodifikaciju_stavke && $data.zahtevZaKodifikaciju_status ){",
        "\t//attach lazy references variables to parent variables",
        "\t$data.zahtevZaKodifikaciju.stavke = $data.zahtevZaKodifikaciju_stavke;",
        "\t$data.zahtevZaKodifikaciju.status = $data.zahtevZaKodifikaciju_status;",
        "\treturn {",
        "\t\t//map zahtevZaKodifikaciju variable to expected task contract input",
        "\t\tzahtevZaKodifikacijuInput: {",
        "\t\t\tstavke: $data.zahtevZaKodifikaciju.stavke.map( it => ({",
        "\t\t\t\tpersistenceId_string: it.persistenceId_string !== undefined ? it.persistenceId_string : null,",
        "\t\t\t\tdokumentZakona: it.dokumentZakona !== undefined ? it.dokumentZakona : null,",
        "\t\t\t\tinstrukcijeZaKodifikaciju: it.instrukcijeZaKodifikaciju !== undefined ? it.instrukcijeZaKodifikaciju : null,",
        "\t\t\t\tskeniranPotpisanZakon: it.skeniranPotpisanZakon !== undefined ? it.skeniranPotpisanZakon : null",
        "\t\t\t})),",
        "\t\t\tstatus: $data.zahtevZaKodifikaciju.status ? {",
        "\t\t\t\tpersistenceId_string: $data.zahtevZaKodifikaciju.status.persistenceId_string !== undefined ? $data.zahtevZaKodifikaciju.status.persistenceId_string : null,",
        "\t\t\t\tstatus: $data.zahtevZaKodifikaciju.status.status !== undefined ? $data.zahtevZaKodifikaciju.status.status : null",
        "\t\t\t} : null,",
        "\t\t\tdatumIniciranja: $data.zahtevZaKodifikaciju.datumIniciranja !== undefined ? $data.zahtevZaKodifikaciju.datumIniciranja : null",
        "\t\t}",
        "\t}",
        "}"
      ],
      "exposed" : false
    },
    "context" : {
      "type" : "url",
      "value" : [
        "../API/bpm/userTask/{{taskId}}/context"
      ],
      "exposed" : false
    },
    "zahtevZaKodifikaciju" : {
      "type" : "url",
      "value" : [
        "../{{context.zahtevZaKodifikaciju_ref.link}}"
      ],
      "exposed" : false
    },
    "zahtevZaKodifikaciju_stavke" : {
      "type" : "url",
      "value" : [
        "{{zahtevZaKodifikaciju|lazyRef:'stavke'}}"
      ],
      "exposed" : false
    },
    "taskId" : {
      "type" : "urlparameter",
      "value" : [
        "id"
      ],
      "exposed" : false
    },
    "zahtevZaKodifikaciju_status" : {
      "type" : "url",
      "value" : [
        "{{zahtevZaKodifikaciju|lazyRef:'status'}}"
      ],
      "exposed" : false
    }
  },
  "hasValidationError" : false,
  "uuid" : "17db1545-538b-4df7-a8d3-7c17769bfb91",
  "type" : "form",
  "description" : "Page generated with Bonita UI designer"
}